qnvip_mcp/__init__.py
qnvip_mcp/main.py
qnvip_mcp/tools/__init__.py
qnvip_mcp/tools/dify_ai_read_img.py
qnvip_mcp/tools/dify_qwen_content_search.py
qnvip_mcp/tools/dify_testcases.py
qnvip_mcp/tools/file_upload.py
qnvip_mcp/tools/md2excel.py
qnvip_mcp-0.0.43.dist-info/METADATA
qnvip_mcp-0.0.43.dist-info/WHEEL
qnvip_mcp-0.0.43.dist-info/entry_points.txt
qnvip_mcp-0.0.43.dist-info/top_level.txt
qnvip_mcp-0.0.43.dist-info/RECORD
