Metadata-Version: 2.4
Name: qnvip-mcp
Version: 0.0.43
Summary: 青年优品mcp工具集
Author: lichaojie
License-Expression: MIT
Project-URL: Homepage, https://github.com/yourusername/my-web-service
Classifier: Programming Language :: Python :: 3
Classifier: Operating System :: OS Independent
Requires-Python: >=3.10
Requires-Dist: fastmcp
Requires-Dist: openpyxl
Requires-Dist: pandas
Requires-Dist: requests
